{"commandString":"zenbot.bat sim binanceus.BTC-USD --period_length=59m --min_periods=91 --markdown_buy_pct=-0.48589237385975803 --markup_sell_pct=0.8977885025241727 --order_type=taker --sell_stop_pct=2 --buy_stop_pct=17 --profit_stop_enable_pct=7 --profit_stop_pct=9 --sar_af=0.4070735038856747 --sar_max_af=0.5493412466509762 --backtester_generation=40 --strategy=sar --days=14 --currency_capital=500 --runGenerations=0 --maxCores=6 --filename=none","queryStart":"2020-09-16T10:51:00.000Z","queryEnd":"2020-10-04T07:11:13.623Z","iteration":40,"startTime":"2020-10-04T07:11:13.639Z","currentTimeString":"2020-10-04 02:35:30","endTime":"2020-10-04T07:11:26.203Z","result":{"params":"module.exports = {\"avg_slippage_pct\":0.045,\"backtester_generation\":40,\"buy_stop_pct\":17,\"markdown_buy_pct\":-0.48589237385975803,\"markup_sell_pct\":0.8977885025241727,\"max_buy_loss_pct\":0,\"max_sell_loss_pct\":0,\"max_slippage_pct\":5,\"min_periods\":91,\"order_poll_time\":5000,\"order_type\":\"taker\",\"period\":\"59m\",\"period_length\":\"59m\",\"profit_stop_enable_pct\":7,\"profit_stop_pct\":9,\"quarentine_time\":10,\"rsi_periods\":14,\"runGenerations\":0,\"sar_af\":0.4070735038856747,\"sar_max_af\":0.5493412466509762,\"selector\":\"binanceus.BTC-USD\",\"sell_stop_pct\":2,\"show_options\":true,\"strategy\":\"sar\",\"symmetrical\":false,\"net_currency\":8.684131413599914,\"start\":\"202009192000\"}","assetPriceLastBuy":"11037.0187","lastAssestValue":10608.08,"profit":-0.033008296640000025,"assetCapital":475.60351476880004,"startCapital":500,"endBalance":483.49585168,"buyHold":479.61211752940136,"vsBuyHold":0.8097656436631931,"wins":0,"losses":1,"errorRate":1,"days":14,"period_length":"59m","min_periods":91,"markdown_buy_pct":-0.48589237385975803,"markup_sell_pct":0.8977885025241727,"order_type":"taker","wlRatio":0,"roi":-3.301,"selector":"binanceus.BTC-USD","strategy":"sar","frequency":0.071}}