{"commandString":"zenbot.bat sim binanceus.BTC-USD --period_length=86m --min_periods=53 --markdown_buy_pct=2.756567003881895 --markup_sell_pct=4.395758405615213 --order_type=taker --sell_stop_pct=30 --buy_stop_pct=0 --profit_stop_enable_pct=5 --profit_stop_pct=17 --ema_acc=0.171590842937264 --cci_periods=89 --rsi_periods=189 --srsi_periods=105 --srsi_k=48 --srsi_d=35 --oversold_rsi=82 --overbought_rsi=40 --oversold_cci=-69 --overbought_cci=15 --constant=0.0036889692553658255 --backtester_generation=97 --strategy=cci_srsi --days=14 --runGenerations=5 --currency_capital=500 --filename=none","queryStart":"2020-10-15T22:00:00.000Z","queryEnd":"2020-11-02T07:08:57.480Z","iteration":97,"startTime":"2020-11-02T07:08:57.486Z","endTime":"2020-11-02T07:09:27.942Z","result":{"params":"module.exports = {}","endBalance":0,"buyHold":0,"vsBuyHold":0,"lastAssestValue":0,"assetPriceLastBuy":0,"wins":0,"losses":-1,"errorRate":100,"days":0,"period_length":0,"min_periods":0,"markdown_buy_pct":0,"markup_sell_pct":0,"order_type":"maker","wlRatio":"Infinity","roi":-1000,"selector":"binanceus.BTC-USD","strategy":"cci_srsi","frequency":0,"assetCapital":0,"startCapital":0,"profit":0}}