{"commandString":"zenbot.bat sim binanceus.BTC-USD --period_length=86m --min_periods=80 --markdown_buy_pct=1.7713811261451755 --markup_sell_pct=0.9207701142012792 --order_type=maker --sell_stop_pct=0 --buy_stop_pct=35 --profit_stop_enable_pct=0 --profit_stop_pct=11 --ema_acc=0.28143659042139013 --cci_periods=178 --rsi_periods=56 --srsi_periods=59 --srsi_k=38 --srsi_d=5 --oversold_rsi=54 --overbought_rsi=65 --oversold_cci=-74 --overbought_cci=8 --constant=0.012290276130753668 --backtester_generation=85 --strategy=cci_srsi --days=14 --runGenerations=5 --currency_capital=500 --filename=none","queryStart":"2020-10-14T07:18:00.000Z","queryEnd":"2020-11-02T07:07:58.507Z","iteration":85,"startTime":"2020-11-02T07:07:58.517Z","endTime":"2020-11-02T07:08:29.455Z","result":{"params":"module.exports = {}","endBalance":0,"buyHold":0,"vsBuyHold":0,"lastAssestValue":0,"assetPriceLastBuy":0,"wins":0,"losses":-1,"errorRate":100,"days":0,"period_length":0,"min_periods":0,"markdown_buy_pct":0,"markup_sell_pct":0,"order_type":"maker","wlRatio":"Infinity","roi":-1000,"selector":"binanceus.BTC-USD","strategy":"cci_srsi","frequency":0,"assetCapital":0,"startCapital":0,"profit":0}}