{
  "trend_ema": [
    {
      "period_length": "81m",
      "min_periods": 87,
      "markdown_buy_pct": 4.289480205227627,
      "markup_sell_pct": 1.1564627596722787,
      "order_type": "maker",
      "sell_stop_pct": 28,
      "buy_stop_pct": 4,
      "profit_stop_enable_pct": 16,
      "profit_stop_pct": 1,
      "trend_ema": 7,
      "oversold_rsi_periods": 48,
      "oversold_rsi": 73
    },
    {
      "period_length": "81m",
      "min_periods": 87,
      "markdown_buy_pct": 4.289480205227627,
      "markup_sell_pct": 1.1564627596722787,
      "order_type": "maker",
      "sell_stop_pct": 28,
      "buy_stop_pct": 4,
      "profit_stop_enable_pct": 16,
      "profit_stop_pct": 7,
      "trend_ema": 7,
      "oversold_rsi_periods": 48,
      "oversold_rsi": 76
    },
    {
      "period_length": "49m",
      "min_periods": 50,
      "markdown_buy_pct": 3.5532409319906098,
      "markup_sell_pct": -0.16716220730634124,
      "order_type": "taker",
      "sell_stop_pct": 0,
      "buy_stop_pct": 15,
      "profit_stop_enable_pct": 0,
      "profit_stop_pct": 18,
      "trend_ema": 3,
      "oversold_rsi_periods": 48,
      "oversold_rsi": 23
    },
    {
      "period_length": "49m",
      "min_periods": 50,
      "markdown_buy_pct": 3.5532409319906098,
      "markup_sell_pct": -0.16716220730634124,
      "order_type": "taker",
      "sell_stop_pct": 0,
      "buy_stop_pct": 15,
      "profit_stop_enable_pct": 0,
      "profit_stop_pct": 18,
      "trend_ema": 3,
      "oversold_rsi_periods": 48,
      "oversold_rsi": 23
    },
    {
      "period_length": "73m",
      "min_periods": 39,
      "markdown_buy_pct": 4.289480205227627,
      "markup_sell_pct": -0.40673311056270967,
      "order_type": "taker",
      "sell_stop_pct": 0,
      "buy_stop_pct": 0,
      "profit_stop_enable_pct": 0,
      "profit_stop_pct": 18,
      "trend_ema": 3,
      "oversold_rsi_periods": 44,
      "oversold_rsi": 23
    },
    {
      "period_length": "81m",
      "min_periods": 87,
      "markdown_buy_pct": 4.289480205227627,
      "markup_sell_pct": 1.1564627596722787,
      "order_type": "taker",
      "sell_stop_pct": 28,
      "buy_stop_pct": 4,
      "profit_stop_enable_pct": 0,
      "profit_stop_pct": 18,
      "trend_ema": 3,
      "oversold_rsi_periods": 48,
      "oversold_rsi": 23
    },
    {
      "period_length": "81m",
      "min_periods": 99,
      "markdown_buy_pct": 3.9956876189993995,
      "markup_sell_pct": 1.1564627596722787,
      "order_type": "maker",
      "sell_stop_pct": 28,
      "buy_stop_pct": 0,
      "profit_stop_enable_pct": 16,
      "profit_stop_pct": 1,
      "trend_ema": 7,
      "oversold_rsi_periods": 11,
      "oversold_rsi": 86
    },
    {
      "period_length": "81m",
      "min_periods": 99,
      "markdown_buy_pct": 3.9956876189993995,
      "markup_sell_pct": 1.1564627596722787,
      "order_type": "taker",
      "sell_stop_pct": 0,
      "buy_stop_pct": 0,
      "profit_stop_enable_pct": 16,
      "profit_stop_pct": 1,
      "trend_ema": 7,
      "oversold_rsi_periods": 11,
      "oversold_rsi": 86
    },
    {
      "period_length": "17m",
      "min_periods": 87,
      "markdown_buy_pct": 4.289480205227627,
      "markup_sell_pct": 1.9148077268855954,
      "order_type": "maker",
      "sell_stop_pct": 0,
      "buy_stop_pct": 30,
      "profit_stop_enable_pct": 7,
      "profit_stop_pct": 19,
      "trend_ema": 33,
      "oversold_rsi_periods": 48,
      "oversold_rsi": 73
    },
    {
      "period_length": "50m",
      "min_periods": 91,
      "markdown_buy_pct": 4.8294347267868485,
      "markup_sell_pct": -0.0878899900611354,
      "order_type": "taker",
      "sell_stop_pct": 8,
      "buy_stop_pct": 0,
      "profit_stop_enable_pct": 10,
      "profit_stop_pct": 20,
      "trend_ema": 39,
      "oversold_rsi_periods": 45,
      "oversold_rsi": 67
    }
  ]
}