{"commandString":"zenbot.bat sim binanceus.BTC-USD --period_length=117m --markdown_buy_pct=0.10430211604541384 --markup_sell_pct=0.5288960375422316 --order_type=maker --sell_stop_pct=37 --buy_stop_pct=0 --profit_stop_enable_pct=17 --profit_stop_pct=4 --kc_size=40 --kc_upper_channel_pct=26.604002492267778 --kc_lower_channel_pct=12.715668461266281 --backtester_generation=95 --strategy=kc --days=5 --currency_capital=450 --noStataSave=false --generateLaunch --runGenerations=1 --filename=none","queryStart":"2020-09-27T07:29:07.000Z","queryEnd":"2020-10-02T23:21:53.179Z","iteration":95,"startTime":"2020-10-02T23:21:53.224Z","currentTimeString":"2020-10-02 12:11:49","endTime":"2020-10-02T23:22:05.402Z","result":{"params":"module.exports = {\"avg_slippage_pct\":0.045,\"backtester_generation\":95,\"buy_stop_pct\":0,\"kc_lower_channel_pct\":12.715668461266281,\"kc_multiplier\":1,\"kc_size\":40,\"kc_upper_channel_pct\":26.604002492267778,\"markdown_buy_pct\":0.10430211604541384,\"markup_sell_pct\":0.5288960375422316,\"max_buy_loss_pct\":0,\"max_sell_loss_pct\":0,\"max_slippage_pct\":5,\"min_periods\":1,\"noStataSave\":\"false\",\"order_poll_time\":5000,\"order_type\":\"maker\",\"period\":\"117m\",\"period_length\":\"117m\",\"profit_stop_enable_pct\":17,\"profit_stop_pct\":4,\"quarentine_time\":10,\"rsi_periods\":14,\"runGenerations\":1,\"selector\":\"binanceus.BTC-USD\",\"sell_stop_pct\":37,\"show_options\":true,\"strategy\":\"kc\",\"symmetrical\":false,\"net_currency\":450,\"start\":\"202009262000\"}","lastAssestValue":10567.39,"profit":0,"assetCapital":0,"startCapital":450,"endBalance":450,"buyHold":441.7333246633814,"vsBuyHold":1.8714176348180567,"wins":0,"losses":0,"errorRate":null,"days":5,"period_length":"117m","min_periods":1,"markdown_buy_pct":0.10430211604541384,"markup_sell_pct":0.5288960375422316,"order_type":"maker","wlRatio":"Infinity","roi":0,"selector":"binanceus.BTC-USD","strategy":"kc","frequency":0}}