{"commandString":"zenbot.bat sim binanceus.BTC-USD --period_length=74m --min_periods=150 --markdown_buy_pct=0 --markup_sell_pct=0 --order_type=maker --sell_stop_pct=50 --buy_stop_pct=0 --profit_stop_enable_pct=5 --profit_stop_pct=5 --buyLevel=65 --sellLevel=60 --tenkenSenPeriods=12 --kijunSenPeriods=74 --senkouSpanPeriods=150 --displacement=22 --backtester_generation=81 --strategy=ichimoku_score --days=5 --currency_capital=450 --noStataSave=false --generateLaunch --runGenerations=1 --filename=none","queryStart":"2020-09-19T15:59:05.000Z","queryEnd":"2020-10-02T23:21:09.351Z","iteration":81,"startTime":"2020-10-02T23:21:09.390Z","currentTimeString":"2020-10-02 14:29:35","endTime":"2020-10-02T23:21:35.428Z","result":{"params":"module.exports = {\"avg_slippage_pct\":0.045,\"backtester_generation\":81,\"buyLevel\":65,\"buy_stop_pct\":0,\"chikouCrossWeight\":1,\"chikouPlacementWeight\":1,\"displacement\":22,\"kijunSenPeriods\":74,\"kumoBreakoutWeight\":1,\"markdown_buy_pct\":0,\"markup_sell_pct\":0,\"max_buy_loss_pct\":0,\"max_sell_loss_pct\":0,\"max_slippage_pct\":5,\"min_periods\":150,\"neutralPoints\":1,\"noStataSave\":\"false\",\"order_poll_time\":5000,\"order_type\":\"maker\",\"period\":\"74m\",\"period_length\":\"74m\",\"pkCrossWeight\":1,\"pricePlacementWeight\":1,\"profit_stop_enable_pct\":5,\"profit_stop_pct\":5,\"quarentine_time\":10,\"rsi_periods\":14,\"runGenerations\":1,\"selector\":\"binanceus.BTC-USD\",\"sellLevel\":60,\"sell_stop_pct\":50,\"senkouCrossWeight\":1,\"senkouSpanPeriods\":150,\"show_options\":true,\"strategy\":\"ichimoku_score\",\"strongPoints\":2,\"symmetrical\":false,\"tenkenSenPeriods\":12,\"tkCrossWeight\":1,\"weakPoints\":0.5,\"net_currency\":7.09154304319992,\"start\":\"202009262000\"}","assetPriceLastBuy":"10782.5200","lastAssestValue":10567.39,"profit":-0.018831505444444473,"assetCapital":433.87599430040007,"startCapital":450,"endBalance":441.52582255,"buyHold":441.3999728959054,"vsBuyHold":0.02851147753111544,"wins":0,"losses":1,"errorRate":1,"days":5,"period_length":"74m","min_periods":150,"markdown_buy_pct":0,"markup_sell_pct":0,"order_type":"maker","wlRatio":0,"roi":-1.883,"selector":"binanceus.BTC-USD","strategy":"ichimoku_score","frequency":0.2}}